FireMirror/__init__.py
FireMirror-0.0.1.dist-info/METADATA
FireMirror-0.0.1.dist-info/WHEEL
FireMirror-0.0.1.dist-info/top_level.txt
FireMirror-0.0.1.dist-info/RECORD
