Metadata-Version: 2.2
Name: FireMirror
Version: 0.0.1
Summary: This is a test package to reserve the name
Home-page: https://github.com/Muhammad Saboor Islam/FireMirror
Author: Muhammad Saboor Islam
Author-email: muhammadsaboor119@gmail.com
Classifier: Programming Language :: Python :: 3
Classifier: License :: OSI Approved :: MIT License
Classifier: Operating System :: OS Independent
Requires-Python: >=3.6
Dynamic: author
Dynamic: author-email
Dynamic: classifier
Dynamic: description
Dynamic: description-content-type
Dynamic: home-page
Dynamic: requires-python
Dynamic: summary
